cryptozaurus/__init__.py
cryptozaurus/main.py
cryptozaurus-0.1.4.dist-info/METADATA
cryptozaurus-0.1.4.dist-info/WHEEL
cryptozaurus-0.1.4.dist-info/entry_points.txt
cryptozaurus-0.1.4.dist-info/licenses/LICENSE
cryptozaurus-0.1.4.dist-info/RECORD
