Metadata-Version: 2.4
Name: cryptozaurus
Version: 0.1.4
Summary: Decryptor for JS's WebCryptoAPI-encrypted timestamps
Project-URL: Homepage, https://github.com/Ovvertone/cryptozaurus
Project-URL: Repository, https://github.com/Ovvertone/cryptozaurus
Author-email: Viacheslav Shirkeev <ooovertone@gmail.com>
License: MIT
License-File: LICENSE
Requires-Python: >=3.10
Requires-Dist: cryptography==45.0.6
